keystone_engine_mac_temporary-0.9.1.post3.data/purelib/keystone/__init__.py
keystone_engine_mac_temporary-0.9.1.post3.data/purelib/keystone/arm64_const.py
keystone_engine_mac_temporary-0.9.1.post3.data/purelib/keystone/arm_const.py
keystone_engine_mac_temporary-0.9.1.post3.data/purelib/keystone/evm_const.py
keystone_engine_mac_temporary-0.9.1.post3.data/purelib/keystone/hexagon_const.py
keystone_engine_mac_temporary-0.9.1.post3.data/purelib/keystone/keystone.py
keystone_engine_mac_temporary-0.9.1.post3.data/purelib/keystone/keystone_const.py
keystone_engine_mac_temporary-0.9.1.post3.data/purelib/keystone/libkeystone.dylib
keystone_engine_mac_temporary-0.9.1.post3.data/purelib/keystone/mips_const.py
keystone_engine_mac_temporary-0.9.1.post3.data/purelib/keystone/ppc_const.py
keystone_engine_mac_temporary-0.9.1.post3.data/purelib/keystone/sparc_const.py
keystone_engine_mac_temporary-0.9.1.post3.data/purelib/keystone/systemz_const.py
keystone_engine_mac_temporary-0.9.1.post3.data/purelib/keystone/x86_const.py
keystone_engine_mac_temporary-0.9.1.post3.dist-info/LICENSE.TXT
keystone_engine_mac_temporary-0.9.1.post3.dist-info/METADATA
keystone_engine_mac_temporary-0.9.1.post3.dist-info/WHEEL
keystone_engine_mac_temporary-0.9.1.post3.dist-info/top_level.txt
keystone_engine_mac_temporary-0.9.1.post3.dist-info/RECORD
